audit_flask/__init__.py
audit_flask/config.py
audit_flask/main.py
audit_flask/audit/__init__.py
audit_flask/audit/kwargs.py
audit_flask/audit/mongoengine.py
audit_flask/audit/sqlalchemy.py
audit_flask/audit/sqlalchemy/__init__.py
audit_flask/audit/sqlalchemy/instances.py
audit_flask/audit/sqlalchemy/sqlalchemy.py
audit_flask/utils/__init__.py
audit_flask/utils/flask.py
audit_flask/utils/json.py
test/__init__.py
test/config.py
test/test_mongoengine.py
test/test_sqlalchemy.py
audit_flask-0.25.7.dist-info/METADATA
audit_flask-0.25.7.dist-info/WHEEL
audit_flask-0.25.7.dist-info/top_level.txt
audit_flask-0.25.7.dist-info/RECORD
