Metadata-Version: 2.1
Name: audit-flask
Version: 0.25.7
Home-page: https://github.com/jrosalesmeza/audit_flask
Author: José Luis Rosales Meza
Author-email: jrosalesmeza@gmail.com
License: MIT
Requires-Dist: flask
Requires-Dist: mongoengine
Requires-Dist: blinker
Requires-Dist: sqlalchemy
